lionsmapper/__init__.py
lionsmapper/lions_map_axis.py
lionsmapper/lions_map_mv_detect.py
lionsmapper/lions_mapper_webcam_capture.py
lionsmapper-8.0.dist-info/licenses/LICENSE
lionsmapper-8.0.dist-info/METADATA
lionsmapper-8.0.dist-info/WHEEL
lionsmapper-8.0.dist-info/top_level.txt
lionsmapper-8.0.dist-info/RECORD
