Metadata-Version: 2.4
Name: lionsmapper
Version: 8.0
Summary: Read Maps Image Files by RGB and get x,y points in pixels values return
Home-page: https://github.com/ssmool/LIONSMAPPERAI
Author: #asytrick
Author-email: eusmool@gmail.com
Classifier: Programming Language :: Python :: 3
Classifier: Operating System :: OS Independent
Requires-Python: >=3.7
License-File: LICENSE
Requires-Dist: opencv-python
Requires-Dist: numpy
Requires-Dist: matplotlib
Requires-Dist: scikit-image
Requires-Dist: webcam
Dynamic: license-file
